jwstapipy/__init__.py
jwstapipy/jwstapipy.py
jwstapipy-0.0.1.dist-info/LICENSE
jwstapipy-0.0.1.dist-info/METADATA
jwstapipy-0.0.1.dist-info/WHEEL
jwstapipy-0.0.1.dist-info/top_level.txt
jwstapipy-0.0.1.dist-info/RECORD
