Metadata-Version: 2.1
Name: jwstapipy
Version: 0.0.1
Summary: Simple async python library for access to data from jwstapi.com
Home-page: https://github.com/malinkinsa/jwstapipy
Download-URL: https://github.com/malinkinsa/jwstapipy/archive/refs/tags/0.0.1.tar.gz
Author: Sergey Malinkin
Author-email: malinkinsa@yandex.ru
License: MIT
Keywords: jwstapi space telescope james webb
Classifier: Development Status :: 5 - Production/Stable
Classifier: Intended Audience :: Developers
Classifier: License :: OSI Approved :: MIT License
Classifier: Operating System :: OS Independent
Classifier: Programming Language :: Python :: 3.7
Classifier: Programming Language :: Python :: 3.8
Classifier: Programming Language :: Python :: 3.9
Classifier: Programming Language :: Python :: 3.10
Classifier: Programming Language :: Python :: 3.11
Classifier: Topic :: Software Development :: Libraries :: Python Modules
License-File: LICENSE
Requires-Dist: asyncio
Requires-Dist: httpx
